odoo/addons/sale_order_line_input/README.rst
odoo/addons/sale_order_line_input/__init__.py
odoo/addons/sale_order_line_input/__manifest__.py
odoo/addons/sale_order_line_input/i18n/ca.po
odoo/addons/sale_order_line_input/i18n/de.po
odoo/addons/sale_order_line_input/i18n/es.po
odoo/addons/sale_order_line_input/i18n/fr.po
odoo/addons/sale_order_line_input/i18n/it.po
odoo/addons/sale_order_line_input/i18n/sale_order_line_input.pot
odoo/addons/sale_order_line_input/i18n/zh_CN.po
odoo/addons/sale_order_line_input/models/__init__.py
odoo/addons/sale_order_line_input/models/sale_order.py
odoo/addons/sale_order_line_input/readme/CONTRIBUTORS.rst
odoo/addons/sale_order_line_input/readme/DESCRIPTION.rst
odoo/addons/sale_order_line_input/readme/USAGE.rst
odoo/addons/sale_order_line_input/static/description/icon.png
odoo/addons/sale_order_line_input/static/description/index.html
odoo/addons/sale_order_line_input/tests/__init__.py
odoo/addons/sale_order_line_input/tests/test_sale_order_line_input.py
odoo/addons/sale_order_line_input/views/sale_order_line_view.xml
odoo12_addon_sale_order_line_input-12.0.1.0.0.99.dev23.dist-info/METADATA
odoo12_addon_sale_order_line_input-12.0.1.0.0.99.dev23.dist-info/WHEEL
odoo12_addon_sale_order_line_input-12.0.1.0.0.99.dev23.dist-info/top_level.txt
odoo12_addon_sale_order_line_input-12.0.1.0.0.99.dev23.dist-info/RECORD
